qoai_qiskit/__init__.py
qoai_qiskit-0.0.1.dist-info/LICENSE.txt
qoai_qiskit-0.0.1.dist-info/METADATA
qoai_qiskit-0.0.1.dist-info/WHEEL
qoai_qiskit-0.0.1.dist-info/top_level.txt
qoai_qiskit-0.0.1.dist-info/RECORD
