Metadata-Version: 2.1
Name: qoai-qiskit
Version: 0.0.1
Summary: Qiskit Quantum API and Access Provider
Author: QuantumOpenAI
Author-email: team@quantumopenai.com
Classifier: Programming Language :: Python :: 3
Classifier: License :: OSI Approved :: MIT License
Classifier: Operating System :: OS Independent
License-File: LICENSE.txt
Requires-Dist: qiskit
